LICENSE
MANIFEST.in
README
setup.cfg
setup.py
docs/Makefile
docs/source/api.rst
docs/source/changelog.rst
docs/source/conf.py
docs/source/development.rst
docs/source/glossary.rst
docs/source/index.rst
docs/source/userguide.rst
docs/source/_themes/nature/theme.conf
docs/source/_themes/nature/static/nature.css_t
docs/source/_themes/nature/static/pygments.css
g_pypi.egg-info/PKG-INFO
g_pypi.egg-info/SOURCES.txt
g_pypi.egg-info/dependency_links.txt
g_pypi.egg-info/entry_points.txt
g_pypi.egg-info/not-zip-safe
g_pypi.egg-info/requires.txt
g_pypi.egg-info/top_level.txt
gpypi/__init__.py
gpypi/cli.py
gpypi/config.py
gpypi/ebuild.py
gpypi/enamer.py
gpypi/exc.py
gpypi/portage_utils.py
gpypi/sdist_ebuild.py
gpypi/trove_map.py
gpypi/utils.py
gpypi/workflow.py
gpypi/templates/ebuild.jinja
gpypi/templates/gpypi.ini
gpypi/tests/__init__.py
gpypi/tests/test_cli.py
gpypi/tests/test_config.py
gpypi/tests/test_ebuild.py
gpypi/tests/test_enamer.py
gpypi/tests/test_portage_utils.py
gpypi/tests/test_pypi.py
gpypi/tests/test_sdist_ebuild.py
gpypi/tests/test_utils.py
gpypi/tests/test_workflow.py
gpypi/tests/setup_samples/gpypi.tests.test_sdist_ebuild.TestSdistEbuild.test_sdist_ebuild.output
gpypi/tests/setup_samples/most_simple_setup.tmpl