Metadata-Version: 1.1
Name: g-pypi
Version: 0.3
Summary: Manages ebuilds for Gentoo Linux using information from Python Package Index
Home-page: https://github.com/iElectric/g-pypi
Author: Domen Kozar
Author-email: domen@dev.si
License: UNKNOWN
Keywords: gentoo linux distribution ebuild package pypi
Platform: UNKNOWN
Classifier: Topic :: Software Development :: Build Tools
Classifier: Topic :: System :: Software Distribution
Classifier: License :: OSI Approved :: BSD License
Classifier: Intended Audience :: Developers
Classifier: Development Status :: 4 - Beta
Classifier: Programming Language :: Python
Classifier: Operating System :: Unix
Classifier: Environment :: Console
